tortus/__init__.py
tortus/tortus.py
tortus/Images/tortus_logo.png
tortus-1.0.2.dist-info/LICENSE.txt
tortus-1.0.2.dist-info/METADATA
tortus-1.0.2.dist-info/WHEEL
tortus-1.0.2.dist-info/top_level.txt
tortus-1.0.2.dist-info/RECORD
