Metadata-Version: 2.1
Name: tortus
Version: 1.0.2
Summary: Easy text annotation in a Jupyter Notebook
Home-page: https://github.com/SiphuLangeni/tortus/
Author: Siphu Langeni
Author-email: szlangeni@gmail.com
License: UNKNOWN
Project-URL: Source Code, https://github.com/SiphuLangeni/tortus/blob/master/src/tortus/tortus.py
Project-URL: Documentation, https://tortus.readthedocs.io/
Keywords: nlp,annotation,labeling,jupyter-notebook,ipywidgets
Platform: UNKNOWN
Classifier: Programming Language :: Python :: 3.6
Classifier: Programming Language :: Python :: 3.7
Classifier: Programming Language :: Python :: 3.8
Classifier: Framework :: Jupyter
Classifier: Operating System :: OS Independent
Classifier: License :: OSI Approved :: GNU General Public License v3 (GPLv3)
Requires-Python: >=3.6
Requires-Dist: pandas (>=1.0.1)
Requires-Dist: ipywidgets (>=7.5.1)
Requires-Dist: ipython (>=7.12.0)
Requires-Dist: jupyter-contrib-nbextensions (>=0.5.1)
Provides-Extra: dev
Requires-Dist: pytest (>=3.7) ; extra == 'dev'
Requires-Dist: check-manifest (==0.10.1) ; extra == 'dev'
Requires-Dist: twine (==3.2.0) ; extra == 'dev'
